otel_declarative/__init__.py
otel_declarative/constants.py
otel_declarative/provider.py
otel_declarative/settings.py
otel_declarative/Config/__init__.py
otel_declarative/Config/extraction_config.py
otel_declarative/Engines/__init__.py
otel_declarative/Engines/converter_registry.py
otel_declarative/Engines/generic_extractor.py
otel_declarative/Engines/log_processors.py
otel_declarative/Engines/model_registry.py
otel_declarative/Engines/object_hydrator.py
otel_declarative/Engines/path_resolver.py
otel_declarative/Engines/Strategies/__init__.py
otel_declarative/Engines/Strategies/converter_strategies.py
otel_declarative/Enums/__init__.py
otel_declarative/Enums/converter_types.py
otel_declarative/Enums/extraction_source.py
otel_declarative/Factories/__init__.py
otel_declarative/Factories/extractor_factory.py
otel_declarative/Infrastructure/__init__.py
otel_declarative/Infrastructure/async_log_engine.py
otel_declarative/Infrastructure/handlers.py
otel_declarative/Interfaces/__init__.py
otel_declarative/Interfaces/extractor.py
otel_declarative/Logging/__init__.py
otel_declarative/Logging/logger_factory.py
otel_declarative/Models/__init__.py
otel_declarative/Models/engine_states.py
otel_declarative/Models/mapping_models.py
otel_declarative/Models/summary_models.py
otel_declarative/Models/Log/__init__.py
otel_declarative/Models/Log/constants.py
otel_declarative/Models/Log/context.py
otel_declarative/Models/Log/mapping.py
otel_declarative/Models/Log/state.py
otel_declarative/Models/Log/topology.py
otel_declarative/Reporters/__init__.py
otel_declarative/Reporters/structured_reporter.py
otel_declarative-0.1.2.dist-info/licenses/LICENSE
otel_declarative-0.1.2.dist-info/METADATA
otel_declarative-0.1.2.dist-info/WHEEL
otel_declarative-0.1.2.dist-info/top_level.txt
otel_declarative-0.1.2.dist-info/RECORD
