Metadata-Version: 2.4
Name: otel-declarative
Version: 0.1.2
Summary: Industrial-grade, declarative OpenTelemetry instrumentation and structured logging engine for Python.
Author-email: Your Name <giangminh443836@gmail.com>
License: MIT License
Project-URL: Homepage, https://github.com/vancer17/otel-declarative.git
Project-URL: Repository, https://github.com/vancer17/otel-declarative.git
Project-URL: Issues, https://github.com/vancer17/otel-declarative.git
Keywords: opentelemetry,observability,tracing,logging,declarative,pydantic,structlog
Classifier: Development Status :: 4 - Beta
Classifier: Intended Audience :: Developers
Classifier: License :: OSI Approved :: MIT License
Classifier: Programming Language :: Python :: 3
Classifier: Programming Language :: Python :: 3.10
Classifier: Programming Language :: Python :: 3.11
Classifier: Programming Language :: Python :: 3.12
Classifier: Topic :: System :: Monitoring
Classifier: Topic :: Software Development :: Libraries :: Python Modules
Requires-Python: >=3.10
License-File: LICENSE
Requires-Dist: opentelemetry-api>=1.20.0
Requires-Dist: opentelemetry-sdk>=1.20.0
Requires-Dist: opentelemetry-exporter-otlp>=1.20.0
Requires-Dist: pydantic>=2.0.0
Requires-Dist: pydantic-settings>=2.0.0
Requires-Dist: structlog>=23.1.0
Requires-Dist: jmespath>=1.0.0
Requires-Dist: pyyaml>=6.0
Requires-Dist: dateparser>=1.1.0
Requires-Dist: humanize>=4.0.0
Requires-Dist: glom>=23.0.0
Provides-Extra: dev
Requires-Dist: pytest>=7.0.0; extra == "dev"
Requires-Dist: mypy>=1.0.0; extra == "dev"
Requires-Dist: types-PyYAML; extra == "dev"
Requires-Dist: types-requests; extra == "dev"
Dynamic: license-file
